llama_index/py.typed
llama_index/vector_stores/baiduvectordb/__init__.py
llama_index/vector_stores/baiduvectordb/base.py
llama_index_vector_stores_baiduvectordb-0.6.1.dist-info/METADATA
llama_index_vector_stores_baiduvectordb-0.6.1.dist-info/WHEEL
llama_index_vector_stores_baiduvectordb-0.6.1.dist-info/licenses/LICENSE
llama_index_vector_stores_baiduvectordb-0.6.1.dist-info/RECORD
